mazikeen/ConsolePrinter.py
mazikeen/DiffBlock.py
mazikeen/GeneratorDiffBlock.py
mazikeen/GeneratorException.py
mazikeen/GeneratorLooper.py
mazikeen/GeneratorMakedirs.py
mazikeen/GeneratorRmdir.py
mazikeen/GeneratorRunBlock.py
mazikeen/GeneratorUtils.py
mazikeen/Loopers.py
mazikeen/MakedirsBlock.py
mazikeen/RmdirBlock.py
mazikeen/RunBlock.py
mazikeen/ScriptDataProcessor.py
mazikeen/ScriptReader.py
mazikeen/SignalHandler.py
mazikeen/Utils.py
mazikeen/__main__.py
mazikeen/version.py
mazikeen-1.2.8.dist-info/LICENSE
mazikeen-1.2.8.dist-info/METADATA
mazikeen-1.2.8.dist-info/WHEEL
mazikeen-1.2.8.dist-info/entry_points.txt
mazikeen-1.2.8.dist-info/top_level.txt
mazikeen-1.2.8.dist-info/RECORD
