Metadata-Version: 2.1
Name: mazikeen
Version: 1.2.8
Summary: Test enviroment for CLI application
Home-page: https://github.com/hanniballar/mazikeen
Author: Neaga Septimiu
Author-email: neagas@gmail.com
License: MIT
Project-URL: Bug Tracker, https://github.com/hanniballar/mazikeen/issues
Platform: UNKNOWN
Classifier: Intended Audience :: Developers
Classifier: Programming Language :: Python :: 3
Classifier: License :: OSI Approved :: MIT License
Classifier: Operating System :: OS Independent
Classifier: Topic :: Software Development :: Testing
Classifier: Topic :: Utilities
Requires-Dist: junit-xml (>=1.8)
Requires-Dist: pyyaml (>=5.4.1)
Provides-Extra: testing
Requires-Dist: xmldiff (==2.4) ; extra == 'testing'
